[
    {
        "start": 0.0,
        "end": 27.86,
        "speaker": 1,
        "text": "هول ورس مسلسل و كنتيت من أواق لبرشحين أو مر كنت أقعد عت بقى معتسذ تمال سسهاني وتعرفت ليهم كنت عام زي اتلليزع عيا كنتو متخوفها كلشان بقال فطه طينه مخرش بس حصل عندي نون لالمستقيه يعني ساعت إنتي تعادي أنا واخده إن أنا يبقى عندي السماريو كامل أول مره أتعامل بطريقه إن أنا ما نجيش الورق كامل "
    },
    {
        "start": 27.86,
        "end": 27.92,
        "speaker": 0,
        "text": ""
    },
    {
        "start": 27.92,
        "end": 34.64,
        "speaker": 1,
        "text": "يهش ا ه مخلاما على االا إحنا نشار هه كانت بجيلنا على اللهو"
    },
    {
        "start": 34.64,
        "end": 34.7,
        "speaker": 0,
        "text": ""
    },
    {
        "start": 34.7,
        "end": 34.88,
        "speaker": 1,
        "text": ""
    },
    {
        "start": 34.88,
        "end": 34.94,
        "speaker": 0,
        "text": ""
    },
    {
        "start": 34.94,
        "end": 35.0,
        "speaker": 1,
        "text": ""
    },
    {
        "start": 35.0,
        "end": 35.06,
        "speaker": 0,
        "text": ""
    },
    {
        "start": 35.06,
        "end": 35.18,
        "speaker": 1,
        "text": ""
    },
    {
        "start": 35.18,
        "end": 36.38,
        "speaker": 0,
        "text": ""
    },
    {
        "start": 36.38,
        "end": 38.18,
        "speaker": 1,
        "text": " "
    },
    {
        "start": 38.18,
        "end": 38.24,
        "speaker": 0,
        "text": ""
    },
    {
        "start": 38.24,
        "end": 38.72,
        "speaker": 1,
        "text": ""
    },
    {
        "start": 38.72,
        "end": 40.82,
        "speaker": 0,
        "text": ""
    },
    {
        "start": 40.82,
        "end": 43.1,
        "speaker": 1,
        "text": " إحنا نح"
    },
    {
        "start": 43.1,
        "end": 43.52,
        "speaker": 0,
        "text": ""
    },
    {
        "start": 43.52,
        "end": 45.5,
        "speaker": 1,
        "text": "نه تأثر عليهم لى ه"
    },
    {
        "start": 45.5,
        "end": 51.74,
        "speaker": 0,
        "text": "نا ولا على ب لدخلنا التصوير تيت لوقت ابتعمح"
    },
    {
        "start": 51.74,
        "end": 56.24,
        "speaker": 1,
        "text": "دخنا القصوير معانا خمساش حله نساش حارج أه أنا حاج إحنا ماجليش مش "
    },
    {
        "start": 56.24,
        "end": 57.08,
        "speaker": 0,
        "text": "عشان حلقه أنا مش "
    },
    {
        "start": 57.08,
        "end": 59.66,
        "speaker": 1,
        "text": "ليش إنتن سبعتخمسلاشر حج"
    },
    {
        "start": 59.66,
        "end": 61.22,
        "speaker": 0,
        "text": "جيمي تس"
    },
    {
        "start": 61.22,
        "end": 61.34,
        "speaker": 1,
        "text": ""
    },
    {
        "start": 61.34,
        "end": 61.4,
        "speaker": 0,
        "text": ""
    },
    {
        "start": 61.4,
        "end": 61.82,
        "speaker": 1,
        "text": ""
    },
    {
        "start": 61.82,
        "end": 66.44,
        "speaker": 0,
        "text": "لس الحله اللي بيخن دي نوكي يمرو أه لكن هما كانوا فيمسطاش"
    },
    {
        "start": 66.44,
        "end": 66.68,
        "speaker": 1,
        "text": "ش"
    },
    {
        "start": 66.68,
        "end": 66.86,
        "speaker": 0,
        "text": ""
    },
    {
        "start": 66.86,
        "end": 66.92,
        "speaker": 1,
        "text": ""
    },
    {
        "start": 66.92,
        "end": 73.88,
        "speaker": 0,
        "text": " ه تسعليه مرفش زي جشعافنلنس حمساشر حلقه بتشتغلهاممش بتشتغل مش عش"
    },
    {
        "start": 73.88,
        "end": 74.42,
        "speaker": 1,
        "text": "لن المع"
    },
    {
        "start": 74.42,
        "end": 82.82,
        "speaker": 0,
        "text": " بتيجي هو برعه مش عافش عن إنتي بيسلمي حلقات بس جد تشتالي والراجل بيصور ناه معاكل يوم"
    },
    {
        "start": 82.82,
        "end": 88.88,
        "speaker": 1,
        "text": "د الحلقه وقتاهبلهم أه على ابكر بعلك ليه تسو تغير مثا نا كنت عملها خط معين"
    },
    {
        "start": 88.88,
        "end": 96.5,
        "speaker": 0,
        "text": "ونا بعد نا غلقالك حوار صحم غير م بيض نطلأيرش بس خلي مثا انا ديكي ناصر يتي وإنتي"
    },
    {
        "start": 96.5,
        "end": 97.64,
        "speaker": 1,
        "text": "دي"
    },
    {
        "start": 97.64,
        "end": 102.2,
        "speaker": 0,
        "text": "شيساهم جيلو وإنتي تتني إنت إنت ف خينهم بسم برح خوزين كمان"
    },
    {
        "start": 102.2,
        "end": 105.14,
        "speaker": 1,
        "text": "إنتبتديب هو المكان يعني البيت السبار"
    },
    {
        "start": 105.14,
        "end": 131.3,
        "speaker": 0,
        "text": "مش هدتاع ال الفمداره لي هذا لعنانه عطب عدهك يا عمسات بحبذ الموضوع ده جد  اسباره أنا كتبت عليها مشهدي يعني السباره الي موجوده في الجليله دي دي مش عليه إنها تكساد لن سمباره شكلها غريب جدا وأاخلمها في ورح سوفو في واد لازم تبتدي عليها مشد أنا لو مكنتش مجود كون شته بالنشقدم سمه  في شويه تفاصيل بتطلع من وح المكان وبتطلع من روحهم"
    },
    {
        "start": 131.3,
        "end": 138.74,
        "speaker": 1,
        "text": "يعني أنا بعد إسبوع من شغلهأنا خلاس بقيت شعيف  حجازي م ش  عر شكاا بيضو لرغاوس"
    },
    {
        "start": 138.74,
        "end": 151.22,
        "speaker": 0,
        "text": "مسل بيشوف ده قدامه أكيد يبقإحنا شخصيه لي ك ربع ره لخم لمك درت بيه تطوري أكتليه شايفاها زي العدين إنت شفعل يعني الكلمه اللي بيه بنفس الأح"
    },
    {
        "start": 151.22,
        "end": 152.3,
        "speaker": 1,
        "text": "نس لج"
    },
    {
        "start": 152.3,
        "end": 160.1,
        "speaker": 0,
        "text": "عنا أنا كمان الربل ده كان معا عم ييعنيل أول واس طبعا أمين فوق لوسط هو جلاني على مري الناس قنينع"
    },
    {
        "start": 160.1,
        "end": 160.16,
        "speaker": 1,
        "text": ""
    },
    {
        "start": 160.16,
        "end": 164.12,
        "speaker": 0,
        "text": "يعني ورا دايما بقوله ده أنا المخرج بالنسبالي مخيكتيش "
    }
]